electrician/__init__.py
electrician/light.py
electrician/light_grouping.py
electrician/version.py
electrician-1.0.0.dist-info/METADATA
electrician-1.0.0.dist-info/RECORD
electrician-1.0.0.dist-info/WHEEL
electrician-1.0.0.dist-info/top_level.txt
