Metadata-Version: 2.1
Name: electrician
Version: 1.0.0
Summary: An abstraction layer to control GPIO devices connected to a raspberry pi
Home-page: https://github.com/pwnbus/electrician
Author: Brandon Myers
Author-email: pwnbus@mozilla.com
License: UNKNOWN
Download-URL: https://github.com/pwnbus/electrician/archive/master.zip
Platform: UNKNOWN
